HISTORY.txt
README.txt
setup.cfg
setup.py
jyu/__init__.py
jyu.z3cform.placeholder.egg-info/PKG-INFO
jyu.z3cform.placeholder.egg-info/SOURCES.txt
jyu.z3cform.placeholder.egg-info/dependency_links.txt
jyu.z3cform.placeholder.egg-info/entry_points.txt
jyu.z3cform.placeholder.egg-info/namespace_packages.txt
jyu.z3cform.placeholder.egg-info/not-zip-safe
jyu.z3cform.placeholder.egg-info/requires.txt
jyu.z3cform.placeholder.egg-info/top_level.txt
jyu/z3cform/__init__.py
jyu/z3cform/placeholder/__init__.py
jyu/z3cform/placeholder/adapters.py
jyu/z3cform/placeholder/config.py
jyu/z3cform/placeholder/configure.zcml
jyu/z3cform/placeholder/directives.py
jyu/z3cform/placeholder/profiles/default/cssregistry.xml
jyu/z3cform/placeholder/profiles/default/jsregistry.xml
jyu/z3cform/placeholder/profiles/default/metadata.xml
jyu/z3cform/placeholder/static/jquery.placeholder.z3cform.js
jyu/z3cform/placeholder/static/jquery.placeholder.z3cform.pack.js
jyu/z3cform/placeholder/static/jquery.watermark.css
jyu/z3cform/placeholder/static/jquery.watermark.pack.js